[
  {
    "_id": "65a0653577b646b67d1f2d51",
    "index": 0,
    "guid": "4938aa78-9f7a-4c76-83f6-f8ad46480be6",
    "isActive": false,
    "balance": "$3,202.10",
    "picture": "http://placehold.it/32x32",
    "age": 31,
    "eyeColor": "blue",
    "name": "Yesenia Blackwell",
    "gender": "female",
    "company": "SINGAVERA",
    "email": "yeseniablackwell@singavera.com",
    "phone": "+1 (880) 415-2062",
    "address": "378 Oxford Street, Condon, Ohio, 919",
    "about": "Lorem est proident proident nisi velit aliqua cillum pariatur deserunt. Incididunt sunt nisi ex esse enim ut sint officia culpa. Quis tempor id ullamco sunt proident dolor cillum sunt officia dolor. Tempor tempor quis tempor ut esse duis ipsum nisi eu. Ad elit id aliquip ea eu culpa excepteur et duis sit. Aliquip fugiat nisi nulla elit deserunt minim.\r\n",
    "registered": "2020-10-21T07:50:04 -01:00",
    "latitude": -14.770132,
    "longitude": -122.237424,
    "tags": [
      "occaecat",
      "fugiat",
      "ex",
      "officia",
      "excepteur",
      "exercitation",
      "elit"
    ],
    "friends": [
      {
        "id": 0,
        "name": "Minnie Strong"
      },
      {
        "id": 1,
        "name": "Frazier Ross"
      },
      {
        "id": 2,
        "name": "Norris Rasmussen"
      }
    ],
    "greeting": "Hello, Yesenia Blackwell! You have 8 unread messages.",
    "favoriteFruit": "apple"
  },
  {
    "_id": "65a065350543fb0ba89fd7ea",
    "index": 1,
    "guid": "2e696021-9583-465e-9dcc-797da12d2cdb",
    "isActive": false,
    "balance": "$3,863.84",
    "picture": "http://placehold.it/32x32",
    "age": 38,
    "eyeColor": "brown",
    "name": "Arnold Clements",
    "gender": "male",
    "company": "ELECTONIC",
    "email": "arnoldclements@electonic.com",
    "phone": "+1 (828) 430-2410",
    "address": "714 Polar Street, Alderpoint, Colorado, 8049",
    "about": "Incididunt Lorem proident sunt elit. Tempor duis proident enim proident est laboris adipisicing labore. Tempor tempor esse aute ex nulla anim et ullamco commodo pariatur sint consectetur consectetur dolor. Minim aliquip sit ad proident mollit anim magna mollit dolor elit quis ipsum do minim. Nostrud cupidatat officia incididunt eiusmod eu cillum id et minim non mollit. Ipsum nulla ea consequat laborum aliquip tempor velit in tempor fugiat velit ut reprehenderit.\r\n",
    "registered": "2016-12-01T09:58:15 -00:00",
    "latitude": 53.619006,
    "longitude": 117.363079,
    "tags": [
      "ea",
      "eu",
      "ullamco",
      "esse",
      "officia",
      "magna",
      "magna"
    ],
    "friends": [
      {
        "id": 0,
        "name": "Maude Love"
      },
      {
        "id": 1,
        "name": "Price Porter"
      },
      {
        "id": 2,
        "name": "Felicia Barnett"
      }
    ],
    "greeting": "Hello, Arnold Clements! You have 8 unread messages.",
    "favoriteFruit": "banana"
  },
  {
    "_id": "65a065358f406db0ac3f331b",
    "index": 2,
    "guid": "af6befe7-1f6a-453f-8aae-633b7f8a05f9",
    "isActive": true,
    "balance": "$3,046.68",
    "picture": "http://placehold.it/32x32",
    "age": 24,
    "eyeColor": "brown",
    "name": "Yvonne Booker",
    "gender": "female",
    "company": "CODACT",
    "email": "yvonnebooker@codact.com",
    "phone": "+1 (953) 505-3847",
    "address": "355 Agate Court, Beyerville, New Jersey, 8991",
    "about": "Do pariatur in tempor reprehenderit veniam sint adipisicing laboris ipsum aute. Ipsum consequat velit qui veniam. Est officia nulla consequat culpa ut anim magna est. Aute eiusmod labore esse anim anim ipsum tempor adipisicing amet incididunt duis cillum sit. Ad pariatur eiusmod eu fugiat elit magna.\r\n",
    "registered": "2016-09-19T02:16:14 -01:00",
    "latitude": -8.527342,
    "longitude": -70.489111,
    "tags": [
      "commodo",
      "commodo",
      "reprehenderit",
      "ut",
      "fugiat",
      "id",
      "sint"
    ],
    "friends": [
      {
        "id": 0,
        "name": "Finley Aguirre"
      },
      {
        "id": 1,
        "name": "Susan Edwards"
      },
      {
        "id": 2,
        "name": "Bridgette Kline"
      }
    ],
    "greeting": "Hello, Yvonne Booker! You have 2 unread messages.",
    "favoriteFruit": "strawberry"
  },
  {
    "_id": "65a065354a583ae796e43167",
    "index": 3,
    "guid": "dffbca10-334e-4962-9b6b-f27d0797af76",
    "isActive": false,
    "balance": "$3,607.94",
    "picture": "http://placehold.it/32x32",
    "age": 33,
    "eyeColor": "blue",
    "name": "Roman Craig",
    "gender": "male",
    "company": "BITREX",
    "email": "romancraig@bitrex.com",
    "phone": "+1 (991) 426-2118",
    "address": "828 Cypress Avenue, Elrama, Massachusetts, 3250",
    "about": "Nulla dolore ut ullamco reprehenderit deserunt consequat fugiat. Aliquip commodo eu ad nulla ad nostrud mollit reprehenderit. Do eiusmod irure sint aliqua ex in laborum nulla. Occaecat irure officia minim cupidatat excepteur minim irure cupidatat. Ut Lorem exercitation cillum eu deserunt exercitation do Lorem veniam deserunt nisi. Do occaecat exercitation esse consectetur tempor do incididunt. Magna reprehenderit non occaecat labore id nisi eiusmod.\r\n",
    "registered": "2021-07-30T09:40:53 -01:00",
    "latitude": 17.56738,
    "longitude": -153.311315,
    "tags": [
      "qui",
      "duis",
      "excepteur",
      "dolor",
      "fugiat",
      "consequat",
      "reprehenderit"
    ],
    "friends": [
      {
        "id": 0,
        "name": "Miles Meyers"
      },
      {
        "id": 1,
        "name": "Drake Wynn"
      },
      {
        "id": 2,
        "name": "Mcbride Harding"
      }
    ],
    "greeting": "Hello, Roman Craig! You have 7 unread messages.",
    "favoriteFruit": "strawberry"
  },
  {
    "_id": "65a065357965f32f5f9e98ca",
    "index": 4,
    "guid": "2924eb6d-79ab-44ef-9f90-65e36e363681",
    "isActive": true,
    "balance": "$1,455.47",
    "picture": "http://placehold.it/32x32",
    "age": 29,
    "eyeColor": "green",
    "name": "Kidd Nielsen",
    "gender": "male",
    "company": "MAXIMIND",
    "email": "kiddnielsen@maximind.com",
    "phone": "+1 (985) 562-3898",
    "address": "716 Pilling Street, Rosine, Vermont, 7428",
    "about": "Commodo cupidatat laborum ut laboris. Officia deserunt id Lorem magna laboris magna enim sint pariatur cillum. Occaecat amet proident velit exercitation. Incididunt irure in ea id. Incididunt occaecat est ut veniam enim voluptate amet pariatur nisi eu labore Lorem. Consequat anim occaecat dolore reprehenderit minim duis sit dolore. Nisi duis id sit in pariatur nulla.\r\n",
    "registered": "2018-06-11T01:20:47 -01:00",
    "latitude": 28.941444,
    "longitude": 56.282369,
    "tags": [
      "ad",
      "cillum",
      "et",
      "magna",
      "nostrud",
      "enim",
      "est"
    ],
    "friends": [
      {
        "id": 0,
        "name": "Terry Rush"
      },
      {
        "id": 1,
        "name": "Hebert Briggs"
      },
      {
        "id": 2,
        "name": "Ramsey Rios"
      }
    ],
    "greeting": "Hello, Kidd Nielsen! You have 9 unread messages.",
    "favoriteFruit": "banana"
  },
  {
    "_id": "65a0653591c44c174dc8fd3e",
    "index": 5,
    "guid": "cbf33450-9275-420f-ac8e-7dbc1642d365",
    "isActive": false,
    "balance": "$2,397.93",
    "picture": "http://placehold.it/32x32",
    "age": 35,
    "eyeColor": "brown",
    "name": "Matthews Webster",
    "gender": "male",
    "company": "JOVIOLD",
    "email": "matthewswebster@joviold.com",
    "phone": "+1 (821) 497-3006",
    "address": "754 Vanderveer Place, Lithium, Virgin Islands, 6336",
    "about": "Aute anim nulla est dolore cupidatat dolor elit anim. Qui exercitation veniam sit cillum nostrud. Enim sint magna aute et Lorem fugiat excepteur dolor ad cillum voluptate amet occaecat commodo. Eu dolor in exercitation aliquip aliqua reprehenderit adipisicing fugiat do duis tempor officia incididunt commodo. Sint deserunt consequat enim eiusmod excepteur qui.\r\n",
    "registered": "2022-07-08T05:24:24 -01:00",
    "latitude": -6.397495,
    "longitude": 154.012601,
    "tags": [
      "elit",
      "anim",
      "ea",
      "incididunt",
      "Lorem",
      "occaecat",
      "cupidatat"
    ],
    "friends": [
      {
        "id": 0,
        "name": "Bean Sanford"
      },
      {
        "id": 1,
        "name": "Bernice Hancock"
      },
      {
        "id": 2,
        "name": "Avila Anthony"
      }
    ],
    "greeting": "Hello, Matthews Webster! You have 1 unread messages.",
    "favoriteFruit": "banana"
  },
  {
    "_id": "65a065355667849e383613fd",
    "index": 6,
    "guid": "f96cfc35-c03a-4c3f-9d9f-67989c489115",
    "isActive": false,
    "balance": "$1,602.07",
    "picture": "http://placehold.it/32x32",
    "age": 30,
    "eyeColor": "brown",
    "name": "Mcguire Gilmore",
    "gender": "male",
    "company": "WATERBABY",
    "email": "mcguiregilmore@waterbaby.com",
    "phone": "+1 (964) 506-3285",
    "address": "394 Union Street, Gordon, Virginia, 4823",
    "about": "Minim est exercitation nostrud ea dolor nisi mollit irure qui ad eiusmod tempor. Consequat non amet aliqua nisi culpa est voluptate anim aliquip exercitation minim consequat laborum irure. Irure dolore velit elit exercitation Lorem. In officia duis do incididunt aute tempor. Occaecat aliqua elit incididunt cupidatat ipsum.\r\n",
    "registered": "2023-07-15T01:30:46 -01:00",
    "latitude": 81.543038,
    "longitude": 6.239758,
    "tags": [
      "laboris",
      "aliqua",
      "adipisicing",
      "amet",
      "esse",
      "Lorem",
      "ullamco"
    ],
    "friends": [
      {
        "id": 0,
        "name": "Acevedo Travis"
      },
      {
        "id": 1,
        "name": "Polly Roman"
      },
      {
        "id": 2,
        "name": "Pickett Copeland"
      }
    ],
    "greeting": "Hello, Mcguire Gilmore! You have 4 unread messages.",
    "favoriteFruit": "apple"
  }
]
